{
  "materials": [
    {
      "id": 1,
      "name": "LATA",
      "icon": "-",
      "buyPrice": 6,
      "sellPrice": 9
    },
    {
      "id": 2,
      "name": "FERRO",
      "icon": "-",
      "buyPrice": 0.4,
      "sellPrice": 0.6
    },
    {
      "id": 3,
      "name": "PERFIL",
      "icon": "-",
      "buyPrice": 7,
      "sellPrice": 10
    },
    {
      "id": 4,
      "name": "CHAPA",
      "icon": "-",
      "buyPrice": 3.5,
      "sellPrice": 7.5
    },
    {
      "id": 5,
      "name": "BLOCO",
      "icon": "-",
      "buyPrice": 2,
      "sellPrice": 6
    },
    {
      "id": 6,
      "name": "CADEIRA",
      "icon": "-",
      "buyPrice": 3,
      "sellPrice": 7.5
    },
    {
      "id": 7,
      "name": "PANELA",
      "icon": "-",
      "buyPrice": 4,
      "sellPrice": 7.5
    },
    {
      "id": 8,
      "name": "RODA",
      "icon": "-",
      "buyPrice": 7,
      "sellPrice": 12
    },
    {
      "id": 9,
      "name": "ACO1",
      "icon": "-",
      "buyPrice": 35,
      "sellPrice": 48.5
    },
    {
      "id": 10,
      "name": "ACO2",
      "icon": "-",
      "buyPrice": 32,
      "sellPrice": 45.5
    },
    {
      "id": 11,
      "name": "METAL",
      "icon": "-",
      "buyPrice": 12,
      "sellPrice": 28
    },
    {
      "id": 12,
      "name": "INSTAL",
      "icon": "-",
      "buyPrice": 12,
      "sellPrice": 22
    },
    {
      "id": 13,
      "name": "CABO",
      "icon": "-",
      "buyPrice": 15,
      "sellPrice": 36.5
    },
    {
      "id": 14,
      "name": "FIO_MX",
      "icon": "-",
      "buyPrice": 2,
      "sellPrice": 11
    },
    {
      "id": 15,
      "name": "CAB_PP",
      "icon": "-",
      "buyPrice": 2,
      "sellPrice": 12
    },
    {
      "id": 16,
      "name": "RADIADOR",
      "icon": "-",
      "buyPrice": 7,
      "sellPrice": 20
    },
    {
      "id": 17,
      "name": "GARIMPO",
      "icon": "-",
      "buyPrice": 1,
      "sellPrice": 2
    },
    {
      "id": 18,
      "name": "INOX",
      "icon": "-",
      "buyPrice": 2.5,
      "sellPrice": 4.5
    },
    {
      "id": 19,
      "name": "MOTOR_G",
      "icon": "-",
      "buyPrice": 12,
      "sellPrice": 28
    },
    {
      "id": 20,
      "name": "BATERIA",
      "icon": "-",
      "buyPrice": 2,
      "sellPrice": 3.5
    },
    {
      "id": 21,
      "name": "TV LED",
      "icon": "-",
      "buyPrice": 2,
      "sellPrice": 5
    },
    {
      "id": 22,
      "name": "TV TUBO",
      "icon": "-",
      "buyPrice": 5,
      "sellPrice": 10
    },
    {
      "id": 23,
      "name": "ZAMARK",
      "icon": "-",
      "buyPrice": 2,
      "sellPrice": 10
    },
    {
      "id": 24,
      "name": "CHUMBO",
      "icon": "-",
      "buyPrice": 2.5,
      "sellPrice": 6
    }
  ],
  "clientsData": {
    "1": {
      "clientName": "Cliente Único"
    }
  },
  "commands": [
    {
      "number": 1,
      "operation": "compra",
      "clientId": 1,
      "clientName": "Cliente Único",
      "date": "2025-05-25",
      "time": "08:22",
      "timestamp": 1748172171906,
      "items": [
        {
          "id": 2,
          "name": "FERRO",
          "weight": 17.2,
          "value": "0.40",
          "total": "6.88",
          "priceEdited": false
        },
        {
          "id": 1,
          "name": "LATA",
          "weight": 5.3,
          "value": "6.00",
          "total": "31.80",
          "priceEdited": false
        }
      ],
      "finalized": true
    },
    {
      "number": 2,
      "operation": "compra",
      "clientId": 1,
      "clientName": "Cliente Único",
      "date": "2025-05-25",
      "time": "08:26",
      "timestamp": 1748172411268,
      "items": [
        {
          "id": 2,
          "name": "FERRO",
          "weight": 0.01,
          "value": "0.40",
          "total": "0.00",
          "priceEdited": false
        },
        {
          "id": 1,
          "name": "LATA",
          "weight": 0.01,
          "value": "6.00",
          "total": "0.06",
          "priceEdited": false
        }
      ],
      "finalized": true
    }
  ],
  "nextCommandNumber": 3,
  "expenses": [],
  "nextExpenseId": 1,
  "unfinishedCommands": {},
  "nextMaterialId": 25,
  "lastSync": "2025-05-25T11:45:22.239Z"
}